ppabam_check_os_ver-0.3.0.dist-info/METADATA
ppabam_check_os_ver-0.3.0.dist-info/WHEEL
ppabam_check_os_ver-0.3.0.dist-info/entry_points.txt
ppabam_check_os_ver/__init__.py
ppabam_check_os_ver/hi.py
ppabam_check_os_ver-0.3.0.dist-info/RECORD
