Metadata-Version: 2.1
Name: ppabam-check-os-ver
Version: 0.3.0
Summary: Detects and outputs the os version.
Author-Email: ppabam <tom@diginori.com>
License: MIT
Project-URL: Homepage, https://github.com/ppabam/ppabam-check-os-ver
Project-URL: Issues, https://github.com/ppabam/ppabam-check-os-ver/issues
Requires-Python: >=3.10
Requires-Dist: stundrg-check-os-ver>=0.2.3
Requires-Dist: check-os-ver>=0.2.1
Requires-Dist: jacob-os-version-check>=0.2.4
Requires-Dist: lucas-check-os-ver>=0.2.1
Requires-Dist: cho-check-os-ver>=0.2.3
Requires-Dist: nunininu-check-os-ver>=0.3.0
Requires-Dist: seo-check-os-version>=0.2.0
Requires-Dist: hj-check-os-version>=0.3.1
